ltz_slack-0.3.2.dist-info/DESCRIPTION.rst
ltz_slack-0.3.2.dist-info/METADATA
ltz_slack-0.3.2.dist-info/RECORD
ltz_slack-0.3.2.dist-info/WHEEL
ltz_slack-0.3.2.dist-info/metadata.json
ltz_slack-0.3.2.dist-info/top_level.txt
slack/__init__.py
slack/chat.py
slack/http_client.py
