Metadata-Version: 2.0
Name: ltz-slack
Version: 0.3.2
Summary: Slack API Client
Home-page: https://github.com/jongoks/lt-slack
Author: Joshua
Author-email: jongoks@gmail.com
License: UNKNOWN
Platform: UNKNOWN
Requires-Dist: requests (>=2.11.1)
Requires-Dist: codecov (>=2.0.5)
